quiz_management/__init__.py
quiz_management/admin.py
quiz_management/apps.py
quiz_management/models.py
quiz_management/tests.py
quiz_management/views.py
django_quiz_management-1.1.dist-info/LICENSE
django_quiz_management-1.1.dist-info/METADATA
django_quiz_management-1.1.dist-info/WHEEL
django_quiz_management-1.1.dist-info/top_level.txt
django_quiz_management-1.1.dist-info/RECORD
