Metadata-Version: 2.1
Name: django-quiz-management
Version: 1.1
Summary: A Django app that makes the use of quiz management and easy to handle
Home-page: https://github.com/krishnaansh/django-quiz-management
Download-URL: https://github.com/krishnaansh/django-quiz-management/releases/download/v1.1/v1.1.zip
Author: Krishna
Author-email: krishnaansh997@gmail.com
License: MIT License
Keywords: django,quiz,management,quiz manage,promotion,question,answer,mcq
Classifier: Environment :: Web Environment
Classifier: Framework :: Django :: 4.1
Classifier: Intended Audience :: Developers
Classifier: License :: OSI Approved :: MIT License
Classifier: Operating System :: OS Independent
Classifier: Programming Language :: Python
Classifier: Programming Language :: Python :: 2.7
Classifier: Programming Language :: Python :: 3.6
Classifier: Programming Language :: Python :: 3.8
Classifier: Topic :: Internet :: WWW/HTTP
Classifier: Topic :: Internet :: WWW/HTTP :: Dynamic Content
Requires-Python: >=3.6
License-File: LICENSE
Requires-Dist: django-nested-admin
